src/__init__.py
src/configs/__init__.py
src/configs/config.py
src/configs/user_conf.py
src/google_api/__init__.py
src/google_api/gcalendar.py
src/main.py
src/metrics/__init__.py
src/metrics/bot_info_metrics.py
src/models/__init__.py
src/models/base_schema.py
src/models/calendar/__init__.py
src/models/calendar/event.py
src/models/calendar/event_meta.py
src/telegram/__init__py
src/telegram/bot_persistence.py
src/telegram/common.py
src/telegram/redispesistence.py
src/telegram/tg_acl.py
src/telegram/tg_calendar.py
src/telegram/tg_wrapper.py
src/telegram/utils.py
src/utils/__init__.py
src/utils/convert.py
src/utils/logger.py
psytican_bot-0.3.8.dist-info/LICENSE
psytican_bot-0.3.8.dist-info/METADATA
psytican_bot-0.3.8.dist-info/WHEEL
psytican_bot-0.3.8.dist-info/entry_points.txt
psytican_bot-0.3.8.dist-info/RECORD
