Metadata-Version: 2.3
Name: psytican-bot
Version: 0.3.8
Summary: Psytican Helper bot
License: MIT
Author: Igor I Shatunov
Author-email: genesis@psytican.com
Requires-Python: >=3.13,<4.0
Classifier: License :: OSI Approved :: MIT License
Classifier: Programming Language :: Python :: 3
Classifier: Programming Language :: Python :: 3.13
Requires-Dist: fastapi (>=0.116,<0.117)
Requires-Dist: furl (>=2.1.3,<3.0.0)
Requires-Dist: google-api-python-client (>=2.123.0,<3.0.0)
Requires-Dist: google-auth-httplib2 (>=0.2.0,<0.3.0)
Requires-Dist: google-auth-oauthlib (>=1.2.0,<2.0.0)
Requires-Dist: oauth2client (>=4.1.3,<5.0.0)
Requires-Dist: pydantic (>=2.9,<3.0)
Requires-Dist: pydantic-settings-vault (>=2.0.0,<3.0.0)
Requires-Dist: pydantic-settings[yaml] (>=2.5,<3.0)
Requires-Dist: python-telegram-bot[job-queue] (>=22,<23)
Requires-Dist: redis (>=5.1.1,<6.0.0)
Requires-Dist: starlette-prometheus (>=0.9.0,<0.10.0)
Requires-Dist: uvicorn (>=0.29.0,<0.30.0)
